setup.py
dc/__init__.py
dc.commonlibrary.egg-info/PKG-INFO
dc.commonlibrary.egg-info/SOURCES.txt
dc.commonlibrary.egg-info/dependency_links.txt
dc.commonlibrary.egg-info/not-zip-safe
dc.commonlibrary.egg-info/top_level.txt
dc/commonlibrary/__init__.py
dc/commonlibrary/object_helper.py