Metadata-Version: 2.4
Name: dc.commonlibrary
Version: 1.0.1
Summary: common library
Dynamic: summary
